accounts/__init__.py
accounts/admin.py
accounts/apps.py
accounts/erros.py
accounts/middleware.py
accounts/models.py
accounts/resolver.py
accounts/response.py
accounts/tests.py
accounts/types.py
accounts/views.py
accounts/auth/__init__.py
accounts/auth/backend.py
accounts/auth/google.py
accounts/auth/token.py
accounts/decorators/__init__.py
accounts/decorators/define.py
accounts/decorators/google.py
accounts/decorators/token.py
accounts/migrations/0001_initial.py
accounts/migrations/__init__.py
django_graphql_google_accounts-0.4.21.dist-info/METADATA
django_graphql_google_accounts-0.4.21.dist-info/WHEEL
django_graphql_google_accounts-0.4.21.dist-info/top_level.txt
django_graphql_google_accounts-0.4.21.dist-info/RECORD
