Metadata-Version: 2.1
Name: django-graphql-google-accounts
Version: 0.4.21
Summary: UNKNOWN
Home-page: https://github.com/YankeeTube/django-graphql-google-accounts
Author: GM Yankee
Author-email: subyankee@gmail.com
License: MIT
Platform: UNKNOWN
Classifier: Development Status :: 3 - Alpha
Classifier: Intended Audience :: Developers
Classifier: Topic :: Software Development :: Build Tools
Classifier: License :: OSI Approved :: MIT License
Classifier: Programming Language :: Python :: 3
Requires-Dist: django
Requires-Dist: PyJWT
Requires-Dist: requests
Requires-Dist: graphene
Requires-Dist: graphene-django
